farmbot_sidecar_starter_pack/__init__.py
farmbot_sidecar_starter_pack/main.py
farmbot_sidecar_starter_pack/state.py
farmbot_sidecar_starter_pack/functions/__init__.py
farmbot_sidecar_starter_pack/functions/api.py
farmbot_sidecar_starter_pack/functions/basic_commands.py
farmbot_sidecar_starter_pack/functions/broker.py
farmbot_sidecar_starter_pack/functions/camera.py
farmbot_sidecar_starter_pack/functions/information.py
farmbot_sidecar_starter_pack/functions/jobs.py
farmbot_sidecar_starter_pack/functions/messages.py
farmbot_sidecar_starter_pack/functions/movements.py
farmbot_sidecar_starter_pack/functions/peripherals.py
farmbot_sidecar_starter_pack/functions/resources.py
farmbot_sidecar_starter_pack/functions/tools.py
farmbot_sidecar_starter_pack-1.6.1.dist-info/METADATA
farmbot_sidecar_starter_pack-1.6.1.dist-info/WHEEL
farmbot_sidecar_starter_pack-1.6.1.dist-info/licenses/LICENSE
farmbot_sidecar_starter_pack-1.6.1.dist-info/RECORD
