Metadata-Version: 2.3
Name: farmbot_sidecar_starter_pack
Version: 1.6.1
Summary: FarmBot Sidecar Starter Pack
Project-URL: homepage, https://github.com/FarmBot-Labs/sidecar-starter-pack
Project-URL: issues, https://github.com/FarmBot-Labs/sidecar-starter-pack/issues
Author: FarmBot Inc.
License-File: LICENSE
Keywords: farmbot,sidecar
Classifier: License :: OSI Approved :: MIT License
Classifier: Operating System :: OS Independent
Classifier: Programming Language :: Python :: 3
Requires-Python: >=3.8
Requires-Dist: paho-mqtt
Requires-Dist: requests
